{
    "sucuess": true,
    "data":{
        "topicList":[{
            "id":1,
            "title":"社会热点",
            "imgUrl": "https://lupic.cdn.bcebos.com/20210629/18682130_14.jpg"
        },{
            "id":2,
            "title":"手绘",
            "imgUrl": "https://lupic.cdn.bcebos.com/20210629/18682130_14.jpg" 
        }],
        "articleList":[{
            "id":1,
            "title":"猎鱼haha",
            "desc":" 原创首发，文责自负。 散文伯乐采薇推荐：这是篇叙事散文，作者用白描的手法生动形象地描摹出热火朝天的水库捞鱼场面。忙碌而有序的初夏傍晚，忽然的一大...",
            "imgUrl": "https://lupic.cdn.bcebos.com/20220107/3085806899_14_600_424.jpg" 
        },{
            "id":2,
            "title":"猎鱼",
            "desc":" 原创首发，文责自负。 散文伯乐采薇推荐：这是篇叙事散文，作者用白描的手法生动形象地描摹出热火朝天的水库捞鱼场面。忙碌而有序的初夏傍晚，忽然的一大...",
            "imgUrl": "https://lupic.cdn.bcebos.com/20220107/3085806899_14_600_424.jpg" 
        },{
            "id":3,
            "title":"猎鱼",
            "desc":" 原创首发，文责自负。 散文伯乐采薇推荐：这是篇叙事散文，作者用白描的手法生动形象地描摹出热火朝天的水库捞鱼场面。忙碌而有序的初夏傍晚，忽然的一大...",
            "imgUrl": "https://lupic.cdn.bcebos.com/20220107/3085806899_14_600_424.jpg" 
        }]
    }
}